cupy_knn/__init__.py
cupy_knn/_version.py
cupy_knn/cuda_util.py
cupy_knn/lbvh_index.py
cupy_knn/cuda/aabb.cuh
cupy_knn/cuda/lbvh.cuh
cupy_knn/cuda/lbvh_kernels.cu
cupy_knn/cuda/morton_code.cuh
cupy_knn/cuda/query.cuh
cupy_knn/cuda/query_knn.cuh
cupy_knn/cuda/query_knn_kernels.cu
cupy_knn/cuda/static_priorityqueue.cuh
cupy_knn/cuda/vec_math.h
cupy_knn-0.4.0.dist-info/LICENSE
cupy_knn-0.4.0.dist-info/METADATA
cupy_knn-0.4.0.dist-info/WHEEL
cupy_knn-0.4.0.dist-info/top_level.txt
cupy_knn-0.4.0.dist-info/RECORD
