Metadata-Version: 2.2
Name: cupy-knn
Version: 0.4.0
Summary: A fast nearest neighbor index cuda implementation for 3D points using a lightweight BVH-tree.
Author-email: Felix Igelbrink <felix.igelbrink@dfki.de>
License: MIT License
Project-URL: Hompage, https://github.com/mortacious/cupy-knn
Project-URL: Issues, https://github.com/mortacious/cupy-knn/issues
Classifier: Environment :: GPU :: NVIDIA CUDA
Classifier: Programming Language :: Python :: 3.8
Classifier: Programming Language :: Python :: 3.9
Classifier: Programming Language :: Python :: 3.10
Classifier: Programming Language :: Python :: 3.11
Classifier: Programming Language :: Python :: 3.12
Classifier: License :: OSI Approved :: MIT License
Classifier: Operating System :: POSIX :: Linux
Classifier: Operating System :: Microsoft :: Windows
Classifier: Intended Audience :: Developers
Classifier: Intended Audience :: Science/Research
Classifier: Topic :: Scientific/Engineering
Classifier: Topic :: Software Development
Requires-Python: >=3.9
License-File: LICENSE
Requires-Dist: numpy
Provides-Extra: default
Requires-Dist: cupy; extra == "default"
Provides-Extra: cuda11x
Requires-Dist: cupy-cuda11x; extra == "cuda11x"
Provides-Extra: cuda12x
Requires-Dist: cupy-cuda12x; extra == "cuda12x"
